fastify/__init__.py
fastify/src/__init__.py
fastify/src/classes/__init__.py
fastify/src/classes/decorators_base.py
fastify/src/classes/json_database.py
fastify/src/classes/mailer.py
fastify/src/classes/template_render.py
fastify/src/constants/__init__.py
fastify/src/constants/content_types.py
fastify/src/constants/decorators.py
fastify/src/constants/events.py
fastify/src/constants/hooks.py
fastify/src/constants/http_methods.py
fastify/src/constants/http_status_code.py
fastify/src/constants/serializers.py
fastify/src/core/__init__.py
fastify/src/core/fastipy.py
fastify/src/core/reply.py
fastify/src/core/request.py
fastify/src/core/request_handler.py
fastify/src/exceptions/__init__.py
fastify/src/exceptions/decorator_already_exists_exception.py
fastify/src/exceptions/duplicate_route_exception.py
fastify/src/exceptions/exception_handler.py
fastify/src/exceptions/fastipy_exception.py
fastify/src/exceptions/file_exception.py
fastify/src/exceptions/invalid_path_exception.py
fastify/src/exceptions/no_event_type.py
fastify/src/exceptions/no_hook_type.py
fastify/src/exceptions/no_http_method_exception.py
fastify/src/exceptions/plugin_exception.py
fastify/src/exceptions/reply_exception.py
fastify/src/helpers/__init__.py
fastify/src/helpers/async_sync_helpers.py
fastify/src/helpers/content_type.py
fastify/src/helpers/route_helpers.py
fastify/src/middlewares/__init__.py
fastify/src/middlewares/cors.py
fastify/src/models/__init__.py
fastify/src/models/body.py
fastify/src/models/file.py
fastify/src/models/form.py
fastify/src/routes/__init__.py
fastify/src/routes/plugin_tree.py
fastify/src/routes/router.py
fastify/src/types/__init__.py
fastify/src/types/fastipy.py
fastify/src/types/plugins.py
fastify/src/types/routes.py
fastify-1.5.3.dist-info/LICENSE
fastify-1.5.3.dist-info/METADATA
fastify-1.5.3.dist-info/WHEEL
fastify-1.5.3.dist-info/RECORD
